tfserver/__init__.py
tfserver/cli.py
tfserver/datasets.py
tfserver/label.py
tfserver/loaders.py
tfserver/normalizer.py
tfserver/predutil.py
tfserver/tflite.py
tfserver/exports/__init__.py
tfserver/exports/skitai/__init__.py
tfserver/exports/skitai/services/__init__.py
tfserver/exports/skitai/services/management.py
tfserver/exports/skitai/services/predict.py
tfserver/pb2/__init__.py
tfserver/pb2/model_pb2.py
tfserver/pb2/model_pb2_grpc.py
tfserver/pb2/predict_pb2.py
tfserver/pb2/predict_pb2_grpc.py
tfserver/pb2/prediction_service_pb2.py
tfserver/pb2/prediction_service_pb2_grpc.py
tfserver/service_models/__init__.py
tfserver-0.4.11.dist-info/LICENSE
tfserver-0.4.11.dist-info/METADATA
tfserver-0.4.11.dist-info/WHEEL
tfserver-0.4.11.dist-info/top_level.txt
tfserver-0.4.11.dist-info/RECORD
