Metadata-Version: 2.1
Name: tfserver
Version: 0.4.11
Summary: Tensor Flow Model Server
Home-page: https://gitlab.com/tfserver/tfserver
Author: Hans Roh
Author-email: hansroh@gmail.com
License: MIT
Download-URL: https://pypi.python.org/pypi/tfserver
Platform: posix
Classifier: License :: OSI Approved :: MIT License
Classifier: Development Status :: 4 - Beta
Classifier: Intended Audience :: Developers
Classifier: Topic :: Scientific/Engineering :: Artificial Intelligence
Classifier: Programming Language :: Python
Classifier: Programming Language :: Python :: 3
License-File: LICENSE
Requires-Dist: atila
Requires-Dist: dill
